[
  {
    "name": "category",
    "key": [
      "category-tops"
    ],
    "filters": [
      "tops"
    ]
  },
  {
    "name": "color",
    "key": [
      "color-beige",
      "color-beige-brown",
      "color-black",
      "color-black-and-white",
      "color-black-n-beige",
      "color-black-n-brown",
      "color-black-n-grey",
      "color-black-n-purple-",
      "color-blue",
      "color-blue,whitenblack",
      "color-blue-n-black",
      "color-blue-n-white",
      "color-brown",
      "color-burgundy",
      "color-carrot",
      "color-checks",
      "color-cobalt",
      "color-coral",
      "color-cream",
      "color-cream-n-red",
      "color-gold",
      "color-green",
      "color-grey",
      "color-hazelnut",
      "color-lavender",
      "color-lemon-yellow",
      "color-maroon",
      "color-marron",
      "color-mint",
      "color-mint-n-white",
      "color-mintnpink",
      "color-multi",
      "color-multicolor",
      "color-mustard",
      "color-mustard-n-lavender",
      "color-navy",
      "color-nude",
      "color-olive",
      "color-orange",
      "color-peach",
      "color-pink",
      "color-pink-n-white",
      "color-plum",
      "color-print",
      "color-purple",
      "color-red",
      "color-rust",
      "color-silver",
      "color-slate",
      "color-stripe",
      "color-taute",
      "color-teal",
      "color-white",
      "color-yellow"
    ],
    "filters": [
      "beige",
      "beige brown",
      "black",
      "black and-white",
      "black n-beige",
      "black n-brown",
      "black n-grey",
      "black n-purple-",
      "blue",
      "blue,whitenblack",
      "blue n-black",
      "blue n-white",
      "brown",
      "burgundy",
      "carrot",
      "checks",
      "cobalt",
      "coral",
      "cream",
      "cream n-red",
      "gold",
      "green",
      "grey",
      "hazelnut",
      "lavender",
      "lemon yellow",
      "maroon",
      "marron",
      "mint",
      "mint n-white",
      "mintnpink",
      "multi",
      "multicolor",
      "mustard",
      "mustard n-lavender",
      "navy",
      "nude",
      "olive",
      "orange",
      "peach",
      "pink",
      "pink n-white",
      "plum",
      "print",
      "purple",
      "red",
      "rust",
      "silver",
      "slate",
      "stripe",
      "taute",
      "teal",
      "white",
      "yellow"
    ]
  },
  {
    "name": "fabric",
    "key": [
      "fabric-cotton-silks",
      "fabric-cottons-n-linens",
      "fabric-crepe",
      "fabric-georgette",
      "fabric-knits",
      "fabric-linen",
      "fabric-moss-lycra",
      "fabric-organza",
      "fabric-other",
      "fabric-poly-crepe",
      "fabric-silks-n-satins",
      "fabric-suiting-light-weight",
      "fabric-suiting-medium-weight",
      "fabric-textured",
      "fabric-velvet",
      "fabric-woolen"
    ],
    "filters": [
      "cotton silks",
      "cottons n-linens",
      "crepe",
      "georgette",
      "knits",
      "linen",
      "moss lycra",
      "organza",
      "other",
      "poly crepe",
      "silks n-satins",
      "suiting light-weight",
      "suiting medium-weight",
      "textured",
      "velvet",
      "woolen"
    ]
  },
  {
    "name": "fit",
    "key": [
      "fit-or-style-fit-n-aline",
      "fit-or-style-straight",
      "fit-or-style-wrap"
    ],
    "filters": [
      "or style-fit-n-aline",
      "or style-straight",
      "or style-wrap"
    ]
  },
  {
    "name": "neckline",
    "key": [
      "neckline-boat",
      "neckline-boat-neck",
      "neckline-collared",
      "neckline-cowl",
      "neckline-high",
      "neckline-high-neck",
      "neckline-notch-neckline",
      "neckline-other",
      "neckline-round",
      "neckline-round-neck",
      "neckline-scoop",
      "neckline-square",
      "neckline-sweetheart",
      "neckline-tie-up",
      "neckline-v-neck",
      "neckline-wrap"
    ],
    "filters": [
      "boat",
      "boat neck",
      "collared",
      "cowl",
      "high",
      "high neck",
      "notch neckline",
      "other",
      "round",
      "round neck",
      "scoop",
      "square",
      "sweetheart",
      "tie up",
      "v neck",
      "wrap"
    ]
  },
  {
    "name": "pattern",
    "key": [
      "pattern-abstract",
      "pattern-african-print",
      "pattern-animal-print",
      "pattern-checks-n-plaids",
      "pattern-color-blocking",
      "pattern-contrast-accent",
      "pattern-embossed-lace",
      "pattern-floral-n-foliage-print",
      "pattern-geometric-prints",
      "pattern-gold-foil-print",
      "pattern-houndstooth",
      "pattern-ikat",
      "pattern-jacquard",
      "pattern-nostalgic-print",
      "pattern-paisley-print",
      "pattern-polka",
      "pattern-schiffli",
      "pattern-solids",
      "pattern-stripes",
      "pattern-textured-print"
    ],
    "filters": [
      "abstract",
      "african print",
      "animal print",
      "checks n-plaids",
      "color blocking",
      "contrast accent",
      "embossed lace",
      "floral n-foliage-print",
      "geometric prints",
      "gold foil-print",
      "houndstooth",
      "ikat",
      "jacquard",
      "nostalgic print",
      "paisley print",
      "polka",
      "schiffli",
      "solids",
      "stripes",
      "textured print"
    ]
  },
  {
    "name": "rise",
    "key": [
      "rise-false"
    ],
    "filters": [
      "false"
    ]
  },
  {
    "name": "sleeve",
    "key": [
      "sleeve-length-half",
      "sleeve-length-long",
      "sleeve-length-long-sleeves",
      "sleeve-length-short",
      "sleeve-length-sleeveless",
      "sleeve-length-sleevless"
    ],
    "filters": [
      "length half",
      "length long",
      "length long-sleeves",
      "length short",
      "length sleeveless",
      "length sleevless"
    ]
  }
]